{
  "gitSyncId": "67531a69050d2337fd42de40_edf31965-b94c-4920-a88e-1eef9b28dab5",
  "id": "Page1_UtilityFunctions.getsyncdTimestamp",
  "pluginId": "js-plugin",
  "pluginType": "JS",
  "unpublishedAction": {
    "actionConfiguration": {
      "encodeParamsToggle": true,
      "jsArguments": [],
      "paginationType": "NONE",
      "timeoutInMillisecond": 10000
    },
    "collectionId": "Page1_UtilityFunctions",
    "confirmBeforeExecute": false,
    "datasource": {
      "isAutoGenerated": false,
      "name": "UNUSED_DATASOURCE",
      "pluginId": "js-plugin"
    },
    "dynamicBindingPathList": [
      {
        "key": "body"
      }
    ],
    "executeOnLoad": false,
    "fullyQualifiedName": "UtilityFunctions.getsyncdTimestamp",
    "name": "getsyncdTimestamp",
    "pageId": "Page1",
    "userSetOnLoad": false
  }
}